Metadata-Version: 2.1
Name: alt-discord-flags-v2
Version: 1.0.0
Summary: A Discord.py extension allowing you to pass flags as arguments.
Home-page: https://github.com/MoonlightCapital/Flag-Parsing
Author: Circuit, MoonlightCapital
License: MIT
Classifier: Development Status :: 5 - Production/Stable
Classifier: License :: OSI Approved :: MIT License
Classifier: Intended Audience :: Developers
Classifier: Natural Language :: English
Classifier: Operating System :: OS Independent
Classifier: Programming Language :: Python :: 3.8
Classifier: Programming Language :: Python :: 3.9
Classifier: Programming Language :: Python :: 3.10
Classifier: Topic :: Software Development :: Libraries
Classifier: Topic :: Software Development :: Libraries :: Python Modules
Classifier: Topic :: Utilities
License-File: LICENSE.md
Requires-Dist: discord.py (>=2.0.1)
